{
  "area": [
    {
      "ypos": 537,
      "height": 14,
      "xpos": 565,
      "width": 38,
      "type": "match",
      "match": 94
    },
    {
      "ypos": 342,
      "height": 31,
      "xpos": 456,
      "width": 146,
      "type": "match"
    },
    {
      "ypos": 222,
      "type": "match",
      "height": 21,
      "xpos": 534,
      "width": 188
    }
  ],
  "properties": [],
  "tags": [
    "import-untrusted-gpg-key",
    "import-known-untrusted-gpg-key"
  ]
}