{
  "area": [
    {
      "width": 105,
      "xpos": 650,
      "type": "match",
      "ypos": 204,
      "height": 55
    },
    {
      "ypos": 434,
      "height": 124,
      "width": 301,
      "xpos": 53,
      "type": "match"
    },
    {
      "type": "match",
      "xpos": 145,
      "width": 10,
      "click_point": {
        "ypos": 5,
        "xpos": 5.5
      },
      "height": 10,
      "ypos": 31
    }
  ],
  "properties": [],
  "tags": [
    "ENV-DISTRI-microos",
    "inst-welcome-no-product-list",
    "languagepicked",
    "license-agreement"
  ]
}