{
  "area": [
    {
      "xpos": 390,
      "ypos": 90,
      "width": 207,
      "height": 35,
      "type": "match"
    },
    {
      "xpos": 48,
      "ypos": 238,
      "width": 173,
      "height": 36,
      "type": "match"
    },
    {
      "xpos": 448,
      "ypos": 140,
      "width": 146,
      "height": 26,
      "type": "match"
    },
    {
      "xpos": 384,
      "ypos": 133,
      "width": 61,
      "height": 58,
      "type": "match"
    }
  ],
  "properties": [],
  "tags": [
    "windows-updates-required-restart"
  ]
}